my_test_proj1_HuangXiaolong/__init__.py
my_test_proj1_HuangXiaolong/example.py
my_test_proj1_HuangXiaolong-0.0.3.dist-info/LICENSE
my_test_proj1_HuangXiaolong-0.0.3.dist-info/METADATA
my_test_proj1_HuangXiaolong-0.0.3.dist-info/WHEEL
my_test_proj1_HuangXiaolong-0.0.3.dist-info/top_level.txt
my_test_proj1_HuangXiaolong-0.0.3.dist-info/RECORD
